cloudshell/__init__.py
cloudshell/huawei/__init__.py
cloudshell/huawei/wdm/__init__.py
cloudshell/huawei/wdm/cli/__init__.py
cloudshell/huawei/wdm/cli/huawei_cli_handler.py
cloudshell/huawei/wdm/cli/huawei_command_modes.py
cloudshell/huawei/wdm/flows/__init__.py
cloudshell/huawei/wdm/flows/huawei_autoload_flow.py
cloudshell/huawei/wdm/flows/huawei_configuration_flow.py
cloudshell/huawei/wdm/flows/huawei_disable_snmp_flow.py
cloudshell/huawei/wdm/flows/huawei_enable_snmp_flow.py
cloudshell/huawei/wdm/flows/huawei_load_firmware_flow.py
cloudshell/huawei/wdm/flows/huawei_run_command_flow.py
cloudshell/huawei/wdm/flows/huawei_state_flow.py
cloudshell/huawei/wdm/helpers/__init__.py
cloudshell/huawei/wdm/helpers/exceptions.py
cloudshell/huawei/wdm/mibs/HUAWEI-IMA-MIB.py
cloudshell/huawei/wdm/mibs/HUAWEI-MIB.py
cloudshell/huawei/wdm/mibs/HUAWEI-PORT-MIB.py
cloudshell/huawei/wdm/mibs/HUAWEI-TC-MIB.py
cloudshell/huawei/wdm/mibs/P-BRIDGE-MIB.py
cloudshell/huawei/wdm/mibs/__init__.py
cloudshell/huawei/wdm/snmp/__init__.py
cloudshell/huawei/wdm/snmp/huawei_snmp_handler.py
tests/__init__.py
tests/huawei/__init__.py
tests/huawei/wdm/__init__.py
tests/huawei/wdm/flows/__init__.py
tests/huawei/wdm/flows/test_huawei_enable_snmp_flow.py
cloudshell_huawei_wdm-1.0.0.dist-info/LICENSE.htm
cloudshell_huawei_wdm-1.0.0.dist-info/METADATA
cloudshell_huawei_wdm-1.0.0.dist-info/WHEEL
cloudshell_huawei_wdm-1.0.0.dist-info/top_level.txt
cloudshell_huawei_wdm-1.0.0.dist-info/RECORD
