Metadata-Version: 2.1
Name: cloudshell-huawei-wdm
Version: 1.0.0
Summary: QualiSystems Huawei WDM specific package
Home-page: http://www.qualisystems.com/
Author: QualiSystems
Author-email: info@qualisystems.com
License: UNKNOWN
Platform: UNKNOWN
Requires-Dist: cloudshell-huawei (<4.1,>=4.0)
